{
    "input": {
        "is_internal": true,
        "external": {
            "storey": 3,
            "upwards": true
        },
        "internal": {
            "lift": 0,
            "storey": 5
        }
    },
    "state": {
        "lifts": [
            {
                "position": 2,
                "targets": [],
                "people": 0
            },
            {
                "position": 2,
                "targets": [],
                "people": 0
            },
            {
                "position": 7,
                "targets": [],
                "people": 0
            }
        ]
    }
}